base69/__init__.py
base69/base69.py
Base_69-0.2.2.dist-info/METADATA
Base_69-0.2.2.dist-info/WHEEL
Base_69-0.2.2.dist-info/top_level.txt
Base_69-0.2.2.dist-info/RECORD
