Metadata-Version: 2.1
Name: Base_69
Version: 0.2.2
Summary: Base 69 encoder and decoder
Home-page: https://github.com/micfun123/Base69
Author: Michael Parker
Author-email: michaelrbparker@protonmail.com
